sgl/__init__.py
sgl/data/__init__.py
sgl/data/base_data.py
sgl/data/base_dataset.py
sgl/data/utils.py
sgl/dataset/__init__.py
sgl/dataset/acm.py
sgl/dataset/actor.py
sgl/dataset/airports.py
sgl/dataset/amazon.py
sgl/dataset/amazon_product.py
sgl/dataset/choose_edge_type.py
sgl/dataset/coauthor.py
sgl/dataset/dblp.py
sgl/dataset/dblp_original.py
sgl/dataset/facebook.py
sgl/dataset/flickr.py
sgl/dataset/github.py
sgl/dataset/karateclub.py
sgl/dataset/linkx_dataset.py
sgl/dataset/nell.py
sgl/dataset/ogbn.py
sgl/dataset/ogbn_mag.py
sgl/dataset/planetoid.py
sgl/dataset/reddit.py
sgl/dataset/twitch.py
sgl/dataset/utils.py
sgl/dataset/webkb.py
sgl/dataset/wikics.py
sgl/etc/__init__.py
sgl/etc/auto_select_edge_type_for_nars.py
sgl/etc/hetero_search.py
sgl/etc/hetero_test.py
sgl/etc/stability_of_subgraph_weight.py
sgl/models/__init__.py
sgl/models/base_model.py
sgl/models/simple_models.py
sgl/models/hetero/__init__.py
sgl/models/hetero/fast_nars_sgc.py
sgl/models/hetero/nars_sign.py
sgl/models/homo/__init__.py
sgl/models/homo/gamlp.py
sgl/models/homo/gamlp_recursive.py
sgl/models/homo/gbp.py
sgl/models/homo/nafs.py
sgl/models/homo/pasca_v1.py
sgl/models/homo/pasca_v2.py
sgl/models/homo/pasca_v3.py
sgl/models/homo/sgc.py
sgl/models/homo/sign.py
sgl/models/homo/ssgc.py
sgl/operators/__init__.py
sgl/operators/base_op.py
sgl/operators/utils.py
sgl/operators/csrc/libcudamatmul.so
sgl/operators/csrc/libmatmul.so
sgl/operators/graph_op/__init__.py
sgl/operators/graph_op/laplacian_graph_op.py
sgl/operators/graph_op/ppr_graph_op.py
sgl/operators/message_op/__init__.py
sgl/operators/message_op/concat_message_op.py
sgl/operators/message_op/iterate_learnable_weighted_message_op.py
sgl/operators/message_op/last_message_op.py
sgl/operators/message_op/learnable_weighted_messahe_op.py
sgl/operators/message_op/max_message_op.py
sgl/operators/message_op/mean_message_op.py
sgl/operators/message_op/min_message_op.py
sgl/operators/message_op/over_smooth_distance_op.py
sgl_dair-0.1.5.dist-info/LICENSE
sgl_dair-0.1.5.dist-info/METADATA
sgl_dair-0.1.5.dist-info/WHEEL
sgl_dair-0.1.5.dist-info/top_level.txt
sgl_dair-0.1.5.dist-info/RECORD
