Metadata-Version: 2.1
Name: sgl-dair
Version: 0.1.5
Summary: Graph Neural Network (GNN) toolkit targeting scalable graph learning
Home-page: https://github.com/PKU-DAIR/SGL
Author: DAIR Lab, PKU
Classifier: Programming Language :: Python :: 3
Classifier: License :: OSI Approved :: MIT License
Classifier: Operating System :: OS Independent
Requires-Python: >=3.6
License-File: LICENSE
Requires-Dist: torch (>=1.8)
Requires-Dist: networkx
Requires-Dist: tqdm
Requires-Dist: numpy (>=1.21)
Requires-Dist: scipy
Requires-Dist: gensim
Requires-Dist: scikit-learn
Requires-Dist: ogb
Requires-Dist: openbox
Requires-Dist: munkres
